yta_random/__init__.py
yta_random-0.0.5.dist-info/LICENSE
yta_random-0.0.5.dist-info/METADATA
yta_random-0.0.5.dist-info/WHEEL
yta_random-0.0.5.dist-info/RECORD
